math_calc/__init__.py
math_calc/calc.py
math_calc/consts.py
math_calc-0.0.1.dist-info/METADATA
math_calc-0.0.1.dist-info/WHEEL
math_calc-0.0.1.dist-info/licenses/LICENSE
math_calc-0.0.1.dist-info/RECORD
