Metadata-Version: 2.1
Name: math-calc
Version: 0.1
Summary: Paquete de ejemplo math_calc
Home-page: http://www.google.es
Author: SMG
Author-email: smaillog@gmail.com
